setup.py
libname/Physics.py
libname/__init__.py
phyforlife.egg-info/PKG-INFO
phyforlife.egg-info/SOURCES.txt
phyforlife.egg-info/dependency_links.txt
phyforlife.egg-info/top_level.txt