Metadata-Version: 1.1
Name: phyforlife
Version: 0.0.1
Summary: A package made for teachers and students of Science. Helps calculate a few things
Home-page: UNKNOWN
Author: Snehashish Laskar age 13
Author-email: <snehashish.laskar@sahyadrischool.org>
License: UNKNOWN
Keywords: python,stream,video stream,camera stream,sockets
Platform: UNKNOWN
Classifier: Development Status :: 1 - Planning
Classifier: Intended Audience :: Developers
Classifier: Programming Language :: Python :: 3
Classifier: Operating System :: Unix
Classifier: Operating System :: MacOS :: MacOS X
Classifier: Operating System :: Microsoft :: Windows
